wakatime/__about__.py
wakatime/__init__.py
wakatime/api.py
wakatime/arguments.py
wakatime/cli.py
wakatime/compat.py
wakatime/configs.py
wakatime/constants.py
wakatime/exceptions.py
wakatime/heartbeat.py
wakatime/language_priorities.py
wakatime/logger.py
wakatime/main.py
wakatime/offlinequeue.py
wakatime/project.py
wakatime/session_cache.py
wakatime/stats.py
wakatime/utils.py
wakatime/dependencies/__init__.py
wakatime/dependencies/c_cpp.py
wakatime/dependencies/data.py
wakatime/dependencies/dotnet.py
wakatime/dependencies/elm.py
wakatime/dependencies/go.py
wakatime/dependencies/haskell.py
wakatime/dependencies/haxe.py
wakatime/dependencies/html.py
wakatime/dependencies/javascript.py
wakatime/dependencies/jvm.py
wakatime/dependencies/objective.py
wakatime/dependencies/php.py
wakatime/dependencies/python.py
wakatime/dependencies/rust.py
wakatime/dependencies/unknown.py
wakatime/packages/__init__.py
wakatime/packages/argparse.py
wakatime/packages/ordereddict.py
wakatime/packages/six.py
wakatime/packages/socks.py
wakatime/packages/certifi/__init__.py
wakatime/packages/certifi/__main__.py
wakatime/packages/certifi/cacert.pem
wakatime/packages/certifi/core.py
wakatime/packages/chardet/__init__.py
wakatime/packages/chardet/big5freq.py
wakatime/packages/chardet/big5prober.py
wakatime/packages/chardet/chardistribution.py
wakatime/packages/chardet/charsetgroupprober.py
wakatime/packages/chardet/charsetprober.py
wakatime/packages/chardet/codingstatemachine.py
wakatime/packages/chardet/compat.py
wakatime/packages/chardet/cp949prober.py
wakatime/packages/chardet/enums.py
wakatime/packages/chardet/escprober.py
wakatime/packages/chardet/escsm.py
wakatime/packages/chardet/eucjpprober.py
wakatime/packages/chardet/euckrfreq.py
wakatime/packages/chardet/euckrprober.py
wakatime/packages/chardet/euctwfreq.py
wakatime/packages/chardet/euctwprober.py
wakatime/packages/chardet/gb2312freq.py
wakatime/packages/chardet/gb2312prober.py
wakatime/packages/chardet/hebrewprober.py
wakatime-13.1.0.dist-info/AUTHORS
wakatime-13.1.0.dist-info/LICENSE
wakatime-13.1.0.dist-info/METADATA
wakatime-13.1.0.dist-info/NOTICE
wakatime-13.1.0.dist-info/WHEEL
wakatime-13.1.0.dist-info/entry_points.txt
wakatime-13.1.0.dist-info/pbr.json
wakatime-13.1.0.dist-info/top_level.txt
wakatime-13.1.0.dist-info/RECORD
